[
    {
        "question": "What is the error in the following C code?\n\n```c\n#include <stdio.h>\n\nint main() {\n    int 5x = 10;\n    printf(\"%d\", 5x);\n    return 0;\n}\n```",
        "options": [
            "Variable name cannot start with a number",
            "Missing semicolon",
            "Incorrect format specifier",
            "No error"
        ],
        "answer": 0,
        "selected": -1
    },
    {
        "question": "Find the error in this C code:\n\n```c\n#include <stdio.h>\n\nint main() {\n    float num = 5.5;\n    printf(\"%d\", num);\n    return 0;\n}\n```",
        "options": [
            "Incorrect format specifier",
            "Float should be declared as int",
            "Printf function is incorrect",
            "No error"
        ],
        "answer": 0,
        "selected": -1
    },
    {
        "question": "What is the mistake in the following C code?\n\n```c\n#include <stdio.h>\n\nint main() {\n    char c = 'AB';\n    printf(\"%c\", c);\n    return 0;\n}\n```",
        "options": [
            "Character variable can only store one character",
            "Wrong format specifier",
            "Incorrect use of printf",
            "No error"
        ],
        "answer": 0,
        "selected": -1
    },
    {
        "question": "Identify the error in this C program:\n\n```c\n#include <stdio.h>\n\nint main() {\n    int a = 10, b = 0;\n    int result = a / b;\n    printf(\"%d\", result);\n    return 0;\n}\n```",
        "options": [
            "Division by zero error",
            "Incorrect variable type",
            "Incorrect printf function",
            "No error"
        ],
        "answer": 0,
        "selected": -1
    },
    {
        "question": "Where is the mistake in this C code?\n\n```c\n#include <stdio.h>\n\nint main() {\n    int arr[5] = {1, 2, 3, 4, 5};\n    printf(\"%d\", arr[5]);\n    return 0;\n}\n```",
        "options": [
            "Array index out of bounds",
            "Incorrect printf function",
            "Array should be of type float",
            "No error"
        ],
        "answer": 0,
        "selected": -1
    },
    {
        "question": "What is the problem in this C program?\n\n```c\n#include <stdio.h>\n\nint main() {\n    int x;\n    printf(\"%d\", x);\n    return 0;\n}\n```",
        "options": [
            "Using an uninitialized variable",
            "Wrong format specifier",
            "Incorrect printf function",
            "No error"
        ],
        "answer": 0,
        "selected": -1
    },
    {
        "question": "Find the error in this C code:\n\n```c\n#include <stdio.h>\n\nint main() {\n    const int num = 10;\n    num = 20;\n    printf(\"%d\", num);\n    return 0;\n}\n```",
        "options": [
            "Cannot modify a constant variable",
            "Incorrect printf function",
            "Wrong format specifier",
            "No error"
        ],
        "answer": 0,
        "selected": -1
    }
]
